slurp/__init__.py
slurp/src/__init__.py
slurp/src/scipy/__init__.py
slurp/src/scipy/_bs.py
slurp/src/scipy/_cc.py
slurp/src/scipy/_f.py
slurp/src/scipy/_gnam.py
slurp/src/scipy/_l.py
slurp/src/scipy/_spline.py
slurp/src/torch_TOREFACTOR/__init__.py
slurp/src/torch_TOREFACTOR/gnam.py
slurp/src/torch_TOREFACTOR/module/__init__.py
slurp/src/torch_TOREFACTOR/module/core.py
slurp/src/torch_TOREFACTOR/module/cyclic_spline.py
slurp/src/torch_TOREFACTOR/module/factor.py
slurp/src/torch_TOREFACTOR/module/linear.py
slurp/src/torch_TOREFACTOR/module/scalar.py
slurp/src/torch_TOREFACTOR/module/spline.py
pyslurp-0.2.0.dist-info/METADATA
pyslurp-0.2.0.dist-info/WHEEL
pyslurp-0.2.0.dist-info/top_level.txt
pyslurp-0.2.0.dist-info/RECORD
