Metadata-Version: 2.4
Name: pyslurp
Version: 0.2.0
Summary: Package to build spline neuralnetwork with syntax similar to GAM packages
Home-page: https://github.com/clarkmaio/slurp
Author: andrea maioli
Author-email: maioliandrea0@gmail.com
Classifier: Programming Language :: Python :: 3
Classifier: License :: OSI Approved :: MIT License
Classifier: Operating System :: OS Independent
Classifier: Topic :: Scientific/Engineering :: Artificial Intelligence
Classifier: Topic :: Scientific/Engineering :: Mathematics
Requires-Python: >=3.7
Requires-Dist: autograd
Requires-Dist: polars
Requires-Dist: scipy
Dynamic: author
Dynamic: author-email
Dynamic: classifier
Dynamic: description-content-type
Dynamic: home-page
Dynamic: requires-dist
Dynamic: requires-python
Dynamic: summary
